MANIFEST.in
README.md
ipysheet.json
setup.cfg
setup.py
ipysheet/__init__.py
ipysheet/_version.py
ipysheet/easy.py
ipysheet/renderer_nbext.py
ipysheet/sheet.py
ipysheet/test_all.py
ipysheet/static/extension-renderer.js
ipysheet/static/extension.js
ipysheet/static/handsontable.js
ipysheet/static/index.js
ipysheet/static/index.js.map
ipysheet/static/renderer.js
ipysheet/static/renderer.js.map
ipysheet_sg.egg-info/PKG-INFO
ipysheet_sg.egg-info/SOURCES.txt
ipysheet_sg.egg-info/dependency_links.txt
ipysheet_sg.egg-info/not-zip-safe
ipysheet_sg.egg-info/requires.txt
ipysheet_sg.egg-info/top_level.txt